lektor_webpack_html_helper.py
lektor_webpack_html_helper-0.1.3.dist-info/METADATA
lektor_webpack_html_helper-0.1.3.dist-info/WHEEL
lektor_webpack_html_helper-0.1.3.dist-info/entry_points.txt
lektor_webpack_html_helper-0.1.3.dist-info/top_level.txt
lektor_webpack_html_helper-0.1.3.dist-info/RECORD
