Metadata-Version: 2.1
Name: lektor-webpack-html-helper
Version: 0.1.3
Summary: Observes the assets directory for html files and copies them into the templates folder.
Home-page: https://github.com/oliverepper/lektor-webpack-html-helper
Author: Oliver Epper
Author-email: oliver.epper@gmail.com
License: MIT
Keywords: Lektor plugin webpack html-webpack-plugin
Platform: UNKNOWN
Classifier: Framework :: Lektor
Classifier: Environment :: Plugins
Requires-Dist: watchdog
